{
  "_comment": "plugin by nuno6573",
  "Name": "DKWDRV",
  "Description": [
    "v1.7.6f Unified Single PS1DRV Replacement",
    "v1.7.6f Remplacement unifié du PS1DRV unique",
    "v1.7.6f Reemplazo unificado de PS1DRV",
    "v1.7.6f Einheitlicher Ersatz für einzelne PS1DRV",
    "v1.7.6f Sostituzione unificata del singolo PS1DRV",
    "v1.7.6f Unified Single PS1DRV-vervanging",
    "v1.7.6f Substituição unificada de PS1DRV"
  ],
  "Icon": "TOOL",
  "CustomIcon": "{cwd}/APPS/PS1_DKWDRV/ic_app_DKWDRV.png",
  "Category": 6,
  "Type": "ELF",
  "Value": {
    "Path": [
      "{cwd}/APPS/PS1_DKWDRV/DKWDRV.ELF",
      "mc?:/PS1_DKWDRV/DKWDRV.ELF",
      "mass?:/APPS/PS1_DKWDRV/DKWDRV.ELF",
      "mass?:/DKWDRV/DKWDRV.ELF"
    ],
    "Args": []
  }
}
